VERSION
data/TW_FDA_nutrition_items.csv
nutrical/__init__.py
nutrical/io.py
nutrical/nutrical.py
nutrical/rank.py
nutrical/tabulate.py
nutrical/taiwan-fda.py
nutrical/utils.py
nutrical-0.0.10.dist-info/METADATA
nutrical-0.0.10.dist-info/WHEEL
nutrical-0.0.10.dist-info/top_level.txt
nutrical-0.0.10.dist-info/RECORD
