Metadata-Version: 2.1
Name: nutrical
Version: 0.0.10
Summary: Nutrition calculation for recipes and ingredients
Home-page: https://github.com/liao961120/nutrical
Author: Yongfu Liao
Author-email: liao961120@gmail.com
License: UNKNOWN
Platform: UNKNOWN
Classifier: Programming Language :: Python :: 3
Classifier: License :: OSI Approved :: MIT License
Classifier: Operating System :: OS Independent
Requires-Dist: Pint
Requires-Dist: tabulate
